odoo/addons/edi_account/README.rst
odoo/addons/edi_account/__init__.py
odoo/addons/edi_account/__manifest__.py
odoo/addons/edi_account/i18n/edi_account.pot
odoo/addons/edi_account/migrations/13.0.2.0.0/pre-migration.py
odoo/addons/edi_account/models/__init__.py
odoo/addons/edi_account/models/account_move.py
odoo/addons/edi_account/readme/CONTRIBUTORS.rst
odoo/addons/edi_account/readme/DESCRIPTION.rst
odoo/addons/edi_account/static/description/icon.png
odoo/addons/edi_account/static/description/index.html
odoo/addons/edi_account/tests/__init__.py
odoo/addons/edi_account/tests/test_edi.py
odoo/addons/edi_account/views/account_journal.xml
odoo/addons/edi_account/views/account_move.xml
odoo/addons/edi_account/views/edi_exchange_record.xml
odoo/addons/edi_account/views/res_partner.xml
odoo13_addon_edi_account-13.0.2.0.1.dist-info/METADATA
odoo13_addon_edi_account-13.0.2.0.1.dist-info/WHEEL
odoo13_addon_edi_account-13.0.2.0.1.dist-info/top_level.txt
odoo13_addon_edi_account-13.0.2.0.1.dist-info/RECORD
